search_engine_parser/__init__.py
search_engine_parser/core/__init__.py
search_engine_parser/core/base.py
search_engine_parser/core/cli.py
search_engine_parser/core/exceptions.py
search_engine_parser/core/utils.py
search_engine_parser/core/engines/__init__.py
search_engine_parser/core/engines/aol.py
search_engine_parser/core/engines/ask.py
search_engine_parser/core/engines/baidu.py
search_engine_parser/core/engines/bing.py
search_engine_parser/core/engines/coursera.py
search_engine_parser/core/engines/duckduckgo.py
search_engine_parser/core/engines/github.py
search_engine_parser/core/engines/google.py
search_engine_parser/core/engines/googlenews.py
search_engine_parser/core/engines/googlescholar.py
search_engine_parser/core/engines/myanimelist.py
search_engine_parser/core/engines/stackoverflow.py
search_engine_parser/core/engines/yahoo.py
search_engine_parser/core/engines/yandex.py
search_engine_parser/core/engines/youtube.py
search_engine_parser/tests/__init__.py
search_engine_parser/tests/test_base.py
search_engine_parser/tests/test_cli.py
search_engine_parser-0.6.8.dist-info/LICENSE
search_engine_parser-0.6.8.dist-info/METADATA
search_engine_parser-0.6.8.dist-info/WHEEL
search_engine_parser-0.6.8.dist-info/entry_points.txt
search_engine_parser-0.6.8.dist-info/top_level.txt
search_engine_parser-0.6.8.dist-info/RECORD
