Metadata-Version: 2.1
Name: search-engine-parser
Version: 0.6.8
Summary: scrapes search engine pages for query titles, descriptions and links
Home-page: https://github.com/bisoncorps/search-engine-parser
Author: Domnan Diretnan, Mmadu Manasseh
Author-email: diretnandomnan@gmail.com
License: MIT
Project-URL: Documentation, https://search-engine-parser.readthedocs.io/en/latest
Project-URL: Source, https://github.com/bisoncorps/search-engine-parser
Keywords: search-engine         search         parser         google         yahoo         bing         yandex         stackoverflow         github         baidu
Classifier: Programming Language :: Python :: 3
Classifier: License :: OSI Approved :: MIT License
Classifier: Operating System :: OS Independent
Requires-Python: >=3.5
Provides-Extra: cli
License-File: LICENSE
